{
  "lemma": "on fleek",
  "examples": [{
    "text": "white teeth , kinda unique , booty on fleek ???"
  }, {
    "text": "distracted doing homework because your eyebrows are on fleek . https : / / t.co / k88TnhWNMB"
  }, {
    "text": "Eyebrows on fleek ?? https : / / t.co / rVd5Ko9kl9"
  }, {
    "text": "I'm taking my mom to get on fleek and then we going to dinner / movie"
  }],
  "status": "novel",
  "senses": [{
    "pos": "r",
    "synonym": "",
    "id": 1,
    "relations": [{
      "type": "hypernym",
      "target": "good: agreeable or pleasing; 'we all had a good time'; 'good manners' <i8696>",
      "relNo": 0
    }],
    "definition": "having a good appearance"
  }]
}
