{
  "lemma": "requote",
  "examples": [{
    "text": "REQUOTE"
  }, {
    "text": "• # KCA • Vote • Retweet • Requote ~ JL ● 16 https : …"
  }, {
    "text": "RETWEET AND REQUOTE FOR JAYE"
  }, {
    "text": "RETWEET AND REQUOTE FOR JAYE"
  }, {
    "text": "Requote"
  }, {
    "text": "Requote"
  }, {
    "text": "Requote and retweet para sulit"
  }, {
    "text": "Requote and retweet para sulit"
  }, {
    "text": "Requote and retweet para sulit"
  }, {
    "text": "100 PHOTOS OF JADINE . TWEET RETWEET AND REQUOTE"
  }],
  "status": "novel",
  "senses": [{
    "pos": "v",
    "synonym": "",
    "id": 1,
    "relations": [{
      "type": "derivation",
      "target": "quote: repeat a passage from; 'He quoted the Bible to her' <i26692>",
      "relNo": 2
    }, {
      "type": "hypernym",
      "target": "quote: repeat a passage from; 'He quoted the Bible to her' <i26692>",
      "relNo": 1
    }],
    "definition": "to quote again"
  }]
}
