{
  "lemma": "my bestfriend",
  "examples": [{
    "text": "My bestfriend ?? https : / / t.co / nJfFeJuZSk"
  }, {
    "text": "HAPPY 20TH BIRTHDAY to my bestfriend and my rock for the last 6 …"
  }, {
    "text": "my bestfriend remember catherine and veronica both 3 deaf for"
  }, {
    "text": "Wtf is a \\ that's my Bestfriend \\\"\" ?\""
  }, {
    "text": "Wtf is a \\ that's my Bestfriend \\\"\" ?\""
  }, {
    "text": "But it's a must I make my bestfriend do something to dude -KekeTweet"
  }, {
    "text": "ImGoingTheVampsNOTTINGHAM MY FAVE MEMORY WAS SOUNDCHECK AND MEETING MY BESTFRIEND ! : D 32 https : / /"
  }, {
    "text": "your best friend ? — I actually meet my bestfriend in kindergarten but we didn't become best fri"
  }, {
    "text": "my mom are so close , she's literally my bestfriend ❤"
  }, {
    "text": "My Bestfriend More Like Sister Is Really Gone ?"
  }],
  "status": "nonlex",
  "senses": [{
    "pos": "n",
    "synonym": "",
    "id": 1,
    "relations": [],
    "definition": ""
  }]
}
