{
  "lemma": "ziam",
  "examples": [{
    "text": "1 year since Ziam"
  }, {
    "text": "1 year since Ziam"
  }, {
    "text": "it's a ziam gc"
  }, {
    "text": "Okay , rt this if you are a ziam girl cuz i really thought i followed zia"
  }, {
    "text": "It's our paradise and It's our ziam zone ."
  }, {
    "text": "idc still larry and ziam af"
  }, {
    "text": "it's annoying , because if you dont like ziam it doesnt mean you're a homophob"
  }, {
    "text": "I READ ABT IT BUT IM TALKING ABT ZIAM HERE !"
  }, {
    "text": "nO JUST COME BACK WITH THE ZIAM"
  }, {
    "text": "her and louis shes so sweet she knows ziam is real yay https : / / t.co"
  }],
  "status": "",
  "senses": [{
    "pos": "",
    "synonym": "",
    "id": 1,
    "relations": [],
    "definition": ""
  }]
}
