{
  "lemma": "*the 5",
  "examples": [{
    "text": "The 5 Things Women Won't Tell You About $ex????????? ?https"
  }, {
    "text": "you had only done the 5 of the required 50 tweets"
  }, {
    "text": "ICYMI : The 5 things that learnt from last week"
  }, {
    "text": "The 5 Biggest # Influencer # Marketing # Trends For"
  }, {
    "text": "Win afternoon tea for two at the 5 * Shangri-La hotel at The Shard , Londo"
  }, {
    "text": "# 9 : The 5 Love Languages : The Secret to Love that"
  }, {
    "text": "# 10 : The 5 Love Languages : The Secret to Love that"
  }, {
    "text": "Which are the 5 most dreadful words ever said by your girlfriend"
  }, {
    "text": "The 5 Biggest Social Media Lies Ever Told https :"
  }, {
    "text": "what's the 5 %"
  }],
  "status": "",
  "senses": [{
    "pos": "",
    "synonym": "",
    "id": 1,
    "relations": [],
    "definition": ""
  }]
}
