{
  "lemma": "barun",
  "examples": [{
    "text": "Barun for ever are you the best # BarunSobtiWeMissYou"
  }, {
    "text": "# BarunSobtiWeMissYou barun sobti we miss you loads we misssss yooooo"
  }, {
    "text": "# BarunSobtiWeMissYou we all proud of you barun love you so much"
  }, {
    "text": "# BarunSobtiWeMissYou we all proud of you barun love you so much"
  }, {
    "text": "# BarunSobtiWeMissYou we miss the one n only barun sobti"
  }, {
    "text": "# BarunSobtiWeMissYou we miss the one n only barun sobti"
  }, {
    "text": "Barun keep rocking : - ) # BarunSobtiWeMissYou"
  }, {
    "text": "we miss u barun # BarunSobtiWeMissYou"
  }, {
    "text": "barun and sanaya so sweet behind the screen of"
  }, {
    "text": "BARUN u r my entire world ! ! without"
  }],
  "status": "name",
  "senses": [{
    "pos": "n",
    "synonym": "",
    "id": 1,
    "relations": [],
    "definition": ""
  }]
}
