{
  "lemma": "watch this",
  "examples": [{
    "text": "Hey Easy Copy My System ! Watch this video - & gt ; https : /"
  }, {
    "text": "Hey Easy Copy My System ! Watch this video - & gt ; https : /"
  }, {
    "text": "Need Video Marketing Services ? Watch This Now ! https : / / t.co /"
  }, {
    "text": "not sure what this hashtag is about but watch this documentary https : / / t.co / 3YNaSJ3IfS"
  }, {
    "text": "For you guys ! Watch this video and get this masturbator for FREE :"
  }, {
    "text": "Hey Easy Copy My System ! Watch this video - & gt ; https : /"
  }, {
    "text": "Watch this video https : / / t.co / GiYN7kSk3N"
  }, {
    "text": "Hi Paul , watch this space for # TeenageCancerGigs news "
  }, {
    "text": "Each time I watch this I think it's edited . Looks like a"
  }, {
    "text": "exploring opportunities to develop specialised logistics services . Watch this space !"
  }],
  "status": "",
  "senses": [{
    "pos": "",
    "synonym": "",
    "id": 1,
    "relations": [],
    "definition": ""
  }]
}
