{
  "lemma": "kill yourself",
  "examples": [{
    "text": "kill yourself https : / / t.co / jQnjSuUDO1"
  }, {
    "text": "Just kill yourself already and stop telling Twitter you want to"
  }, {
    "text": "kill yourself you ugly ass roach looking piece of rat"
  }, {
    "text": "anymore and at 5 am you just wanna kill yourself"
  }, {
    "text": "spent so much just kill yourself no one else is in the shop like"
  }, {
    "text": "brain : the only way is to ... Kill Yourself"
  }, {
    "text": "pece when you finish a video anymore , kill yourself faggot . Unsubbed and flagge"
  }, {
    "text": "pleas kill yourself"
  }, {
    "text": "asked you to follow me you dickhead , kill yoursel"
  }, {
    "text": "Kill yourself"
  }],
  "status": "",
  "senses": [{
    "pos": "",
    "synonym": "",
    "id": 1,
    "relations": [],
    "definition": ""
  }]
}
