{
  "lemma": "see ya",
  "examples": [{
    "text": "listened to my idea then laddddd ? see ya then ! Xx"
  }, {
    "text": "HAPPY BIRTHDAY to my homie see ya tonight ?"
  }, {
    "text": "yea we'll see ya"
  }, {
    "text": "Thank you ??? see ya on # TwitTv w https : / /"
  }, {
    "text": "ok see ya there https : / / t.co / VYHlnHf509"
  }, {
    "text": "birthday , Have a great year ahead ! See ya around ! ?"
  }, {
    "text": "I see ya loyalty paying off ..."
  }, {
    "text": "! Thanks for errthang since 2nd year and see ya soon"
  }, {
    "text": "I SEE YA GIRL …"
  }, {
    "text": "the Flop ! ! Gonna be fun ! See ya at the show ! # bonecollector # hardcore"
  }],
  "status": "",
  "senses": [{
    "pos": "",
    "synonym": "",
    "id": 1,
    "relations": [],
    "definition": ""
  }]
}
