{
  "lemma": "*fuck",
  "examples": [{
    "text": "Got kicked out of class for saying fuck ! ?"
  }, {
    "text": "whatever they want , they don't give a fuck https : / / t.co / Xrq6ESPIK"
  }, {
    "text": "told her my fetish now she fuck me w no socks on"
  }, {
    "text": "... idgaf abt sht when im mad . fuck everybody ."
  }, {
    "text": "Fuck it's Wednesday . Fuck there is a con"
  }, {
    "text": "| fuck |"
  }, {
    "text": "/ / t.co / 7UKxSubwYA? Sexy girls to fuck in your city ✅ Fully free now?"
  }, {
    "text": ": / / t.co / JKMMKUlkWe? Women to fuck in your place ✅ Join for free now?"
  }, {
    "text": ": / / t.co / Dimz2eV867? Women to fuck in your place ✅ Join for free now?"
  }, {
    "text": "just leave him wtf ? He's sound as fuck stop being weird man"
  }],
  "status": "",
  "senses": [{
    "pos": "",
    "synonym": "01429048-v (have sexual intercourse with; \\\"\"This student sleeps with everyone in her dorm\\\"\"; \\\"\"Adam knew Eve\\\"\"; \\\"\"Were you ever intimate with this man?\\\"\");00847651-n (slang for sexual intercourse",
    "id": 1,
    "relations": [],
    "definition": ""
  }]
}
