{
  "examples": [{
    "text": "might end up injuring yourself , which will fuck you up in the longterm . and as lon"
  }, {
    "text": "to take cover from the shockwave that would fuck you up if you were standing in the window"
  }],
  "lemma": "fuck up",
  "senses": [{
    "pos": "v",
    "synonym": "smash up: damage or destroy as if by violence; 'The teenager banged up the car of his mother' <i29563>",
    "id": 1,
    "relations": [{
      "type": "derivation",
      "target": "fuck: slang for sexual intercourse <i39847>",
      "relNo": 1
    }],
    "definition": ""
  }],
  "status": "vulgar",
  "editorId": "jmccrae"
}
