{
  "lemma": "fetty",
  "examples": [{
    "text": "Fetty Wap puts me in a good mood"
  }, {
    "text": "Bruh Fetty Wap said \\ girl you so fine swear\""
  }, {
    "text": "Wish I was going to see Fetty wap in 2 weeks but I'm not so"
  }, {
    "text": "MECHIEDEUCE NEWS The Best Quotes From Fetty Wap ’ s Interview With Trevor Noah https"
  }, {
    "text": "Freaky Bia - French Montana ft Fetty Wap & amp ; Monty Zoo"
  }, {
    "text": "‘ Young Thug Vs Fetty Wap : Twerk For These Jimmy Choos ’"
  }, {
    "text": "The Best Quotes From Fetty Wap ’ s Interview With Trevor Noah https"
  }, {
    "text": "# Nowplaying Fetty Wap - My Way"
  }, {
    "text": "best friends were her my pop and the fetty in my pocket lol like where the fuck"
  }, {
    "text": "up 3 hours before my class to get Fetty tickets..This is dedication"
  }],
  "status": "name",
  "senses": [{
    "pos": "n",
    "synonym": "",
    "id": 1,
    "relations": [],
    "definition": ""
  }]
}
