{
  "lemma": "i miss you",
  "examples": [{
    "text": "I miss you too ?"
  }, {
    "text": "I miss you"
  }, {
    "text": "I miss you , my friend?❤"
  }, {
    "text": "I miss you . So bad?"
  }, {
    "text": "Happy birthday to you i miss you so much # sister"
  }, {
    "text": "I miss you baby : ( ( ( im sad cause"
  }, {
    "text": "I love you Audrey ! ! I miss you so much ! thank you❤️❤️❤️"
  }, {
    "text": "i miss you ? !"
  }, {
    "text": "here to bask in the glory ! ! I miss you so much https : / / t.co /"
  }, {
    "text": "I miss you ❤"
  }],
  "status": "nonlex","editorId": "",
  "senses": [{
    "pos": "n",
    "synonym": "",
    "id": 1,
    "relations": [],
    "definition": ""
  }]
}
