{
  "lemma": "mehn",
  "examples": [{
    "text": "Oya now \\ I can \\\"\" oh mehn ! ! ! so you can't defend your\""
  }, {
    "text": "rose to 3rd trending topic this night ... Mehn"
  }, {
    "text": "Super Eagles mehn . What a pity ."
  }, {
    "text": "Aw mehn I'm lacking confidence . So I'm going to"
  }, {
    "text": "i'm a rABBIT MEHN"
  }, {
    "text": "Mehn i dont need to stay in the states"
  }, {
    "text": "to work this early morning , fucking tired meh"
  }, {
    "text": "Mehn ! Benteke should come back to Villa"
  }, {
    "text": "Ycee on the down with this Omo Alhaji mehn ..."
  }, {
    "text": "They thought people won't query , mehn were they wron"
  }],
  "status": "novel","editorId": "",
  "senses": [{
    "pos": "n",
    "synonym": "man: the generic use of the word to refer to any human being; 'it was every man for himself' <i91186>",
    "id": 1,
    "relations": [{
      "type": "domain_region",
      "target": "Mexico: a republic in southern North America; became independent from Spain in 1810 <i82822>",
      "relNo": 1
    }],
    "definition": ""
  }]
}
