{
  "lemma": "dark power",
  "examples": [{
    "text": "world might be a surprising source of a dark power ... More for Pisces https : / /"
  }, {
    "text": "world might be a surprising source of a dark power ... More for Pisces https : / /"
  }, {
    "text": "world might be a surprising source of a dark power ... More for Pisces https : / /"
  }, {
    "text": "world might be a surprising source of a dark power ... More for Pisces https : / /"
  }, {
    "text": "world might be a surprising source of a dark power ... More for Pisces https : / /"
  }, {
    "text": "world might be a surprising source of a dark power ... More for Pisces https : / /"
  }, {
    "text": "world might be a surprising source of a dark power ... More for Pisces https : / /"
  }, {
    "text": "world might be a surprising source of a dark power ... More for Pisces https : / /"
  }, {
    "text": "world might be a surprising source of a dark power ... More for Pisces https : / /"
  }, {
    "text": "world might be a surprising source of a dark power ... More for Pisces https : / /"
  }],
  "status": "nonlex","editorId": "",
  "senses": [{
    "pos": "n",
    "synonym": "",
    "id": 1,
    "relations": [],
    "definition": ""
  }]
}
