{
  "lemma": "*nacreous",
  "examples": [{
    "text": "ikr they're called nacreous clouds / / / /"
  }, {
    "text": "These nacreous clouds were shades of pink and green as"
  }, {
    "text": "# nacreous # clouds https : / / t.co /"
  }, {
    "text": "# whitbysnaps # nacreous https : / / t.co / …"
  }, {
    "text": "BBC News - Colourful nacreous clouds spark aurora borealis reports https : /"
  }, {
    "text": "# whitbysnaps # nacreous https : / / t.co / …"
  }, {
    "text": "The nacreous clouds I believe is the correct … https"
  }, {
    "text": "pano : ) At centre , the # nacreous , 'mother of pearl' clouds , to th"
  }, {
    "text": "Explainer : What Are The \\ Nacreous Clouds \\\"\" Lighting Up The Winter Skies ?\""
  }, {
    "text": "Rare nacreous clouds https : / / t.co / IuZ7Hj22vV"
  }],
  "status": "","editorId": "",
  "senses": [{
    "pos": "",
    "synonym": "00282886-a (having a play of lustrous rainbow colors; \\\"\"an iridescent oil slick\\\"\"; \\\"\"nacreous (or pearlescent) clouds looking like mother-of-pearl\\\"\"; \\\"\"a milky opalescent (or opaline) luster\\\"\");03007631-a (consisting of or resembling mother-of-pearl",
    "id": 1,
    "relations": [],
    "definition": ""
  }]
}
