{
  "lemma": "oh fuck",
  "examples": [{
    "text": "oh fuck her"
  }, {
    "text": "\\ Hi there would you like to oh fuck theres an alligator \\\"\" is just a sentence\""
  }, {
    "text": "cummy4mommy : Oh fuck mom ! I ’ m gonna make a"
  }, {
    "text": "Oh fuck why I keep writing to myself like you"
  }, {
    "text": "Oh fuck ?? https : / / t.co / YmpplNqqz5"
  }, {
    "text": "oh fuck ?? https : / / t.co / vychHoojQn"
  }, {
    "text": "oh fuck I'm sorry Carmen so if I just sit"
  }, {
    "text": "Oh fuck , theres that giant spider from yesterday "
  }, {
    "text": "oh fuck"
  }, {
    "text": "OH FUCK"
  }],
  "status": "","editorId": "",
  "senses": [{
    "pos": "",
    "synonym": "",
    "id": 1,
    "relations": [],
    "definition": ""
  }]
}
