{
  "lemma": "lulz",
  "examples": [{
    "text": "LULZ"
  }, {
    "text": "hundreds of \\ anime bewbs \\\"\" for the lulz\""
  }, {
    "text": "# G0DsJester # Daeshbag # TrollingISIS # lulz https : / / t.co / UnkroRJCSR"
  }, {
    "text": "And for your # lulz of the day , Chelsea Clinton accidentally say"
  }, {
    "text": "I had a good night lulz"
  }, {
    "text": "# POTUS knows what he's doing ? # Lulz # GOPDebate # Idiots"
  }, {
    "text": "I will try and fuck up . # lulz"
  }, {
    "text": "im A dOXEd LosUr LULZ"
  }, {
    "text": "One more for the lulz taken with my screenshot button with light filtering"
  }, {
    "text": "Lulz bad guys who like to explain too much"
  }],
  "status": "","editorId": "",
  "senses": [{
    "pos": "",
    "synonym": "",
    "id": 1,
    "relations": [],
    "definition": ""
  }]
}
