{
  "examples": [{
    "text": "by / Mañana # Estreno - # ALoNatural ( Prod ."
  }, {
    "text": "I am gonna get it . ?jorge_arranz ( Mañana nuevo post en el blog con … https"
  }, {
    "text": "# CopaLatamLoL # lolesportsla GG Furious ... Mañana se gana vs HAFNET ! # GoKLG https"
  }, {
    "text": "mañana voyy"
  }, {
    "text": "wobbling around the court during the dodgeball game mañana"
  }, {
    "text": "Toda la mañana adultando . Siendo adulto . All over the"
  }, {
    "text": "are auctioning off a week at Casa de Mañana at the opening 2 / 6"
  }, {
    "text": "Coldplay on replay to get ready for mañana"
  }, {
    "text": "a ver the walking dead toda la pinche mañana"
  }, {
    "text": "I got an AP quiz mañana but I'm over here watching videos on how"
  }],
  "lemma": "mañana",
  "senses": [{
    "pos": "n",
    "synonym": "tomorrow: the day after today; 'what are our tasks for tomorrow?' <i116860>",
    "id": 1,
    "relations": [{
      "type": "loanword",
      "target": "Spanish: the Romance language spoken in most of Spain and the countries colonized by Spain <i73223>",
      "relNo": 1
    }],
    "definition": ""
  }],
  "status": "novel",
  "editorId": "jmccrae"
}
