{
  "examples": [{
    "text": "to your # SmurfsVillage Island to host a smurftastic celebration every day ! https : / /"
  }, {
    "text": "to your # SmurfsVillage Island to host a smurftastic celebration every day ! https : / /"
  }, {
    "text": "to your # SmurfsVillage Island to host a smurftastic celebration every day ! https : / /"
  }, {
    "text": "to your # SmurfsVillage Island to host a smurftastic celebration every day ! https : / /"
  }, {
    "text": "to your # SmurfsVillage Island to host a smurftastic celebration every day ! https : / /"
  }, {
    "text": "to your # SmurfsVillage Island to host a smurftastic celebration every day ! https : / /"
  }, {
    "text": "to your # SmurfsVillage Island to host a smurftastic celebration every day ! https : / /"
  }, {
    "text": "to your # SmurfsVillage Island to host a smurftastic celebration every day ! https : / /"
  }, {
    "text": "to your # SmurfsVillage Island to host a smurftastic celebration every day ! https : / /"
  }, {
    "text": "to your # SmurfsVillage Island to host a smurftastic celebration every day ! https : / /"
  }],
  "lemma": "smurftastic",
  "senses": [{
    "pos": "n",
    "synonym": "",
    "id": 1,
    "relations": [],
    "definition": ""
  }],
  "status": "name",
  "editorId": "jmccrae"
}
