{
  "lemma": "whoriental",
  "examples": [{
    "text": "# livetweet # whoriental # services # amateurs"
  }, {
    "text": "# kita # whoriental # services # amateurs"
  }, {
    "text": "# amateurs # kita # whoriental # services"
  }, {
    "text": "# whoriental # livetweet # kita # amateurs"
  }, {
    "text": "# kita # whoriental # services # livetweet"
  }, {
    "text": "# livetweet # whoriental # services # kita"
  }, {
    "text": "# kita # whoriental # amateurs # livetweet # services"
  }, {
    "text": "# livetweet # whoriental # services # kita"
  }, {
    "text": "# amateurs # kita # services # whoriental"
  }, {
    "text": "porn # sexy # thai # video # whoriental # xxx"
  }],
  "status": "","editorId": "",
  "senses": [{
    "pos": "",
    "synonym": "",
    "id": 1,
    "relations": [],
    "definition": ""
  }]
}
