{
  "examples": [{
    "text": "pupper family"
  }, {
    "text": "Help a pupper https : / / t.co / SeUrapxvHk"
  }, {
    "text": "it's official i need a pupper or i will die"
  }, {
    "text": "vacuum that pupper up"
  }, {
    "text": "i'm a fluffy pupper givin boops and licks and hugs wag wag"
  }, {
    "text": "my pupper just walked into my room , jumped o"
  }, {
    "text": "I am baekhyun's pupper https : / / t.co / h9VzSXMMPm"
  }, {
    "text": "best pupper ever"
  }, {
    "text": "I need a pupper and a vacation ."
  }],
  "lemma": "pupper",
  "senses": [{
    "pos": "n",
    "synonym": "puppy: a young dog <i42298>",
    "id": 1,
    "relations": [{
      "type": "derivation",
      "target": "puppy: a young dog <i42298>",
      "relNo": 1
    }],
    "definition": ""
  }],
  "status": "novel",
  "editorId": "jmccrae"
}
