{
  "examples": [{
    "text": "Omg . Aki ang gwapo mo kagabi sa Wattpad ? I want to"
  }, {
    "text": "justin bieber honey my loves so gwapo ??"
  }, {
    "text": "so gwapo naman this guy ? https : / /"
  }, {
    "text": "ANG GWAPO NI ENRIQUE"
  }, {
    "text": "ANG GWAPO NI ENRIQUE"
  }, {
    "text": "ANG GWAPO NI ENRIQUE"
  }, {
    "text": "this gwapo human being wanna get slimed . So VOTE"
  }, {
    "text": "this gwapo human being wanna get slimed . So VOTE"
  }],
  "lemma": "gwapo",
  "senses": [{
    "pos": "a",
    "synonym": "handsome: pleasing in appearance especially by reason of conformity to ideals of form and proportion; 'a fine-looking woman'; 'a good-looking man'; 'better-looking than her sister'; 'very pretty but not so extraordinarily handsome'- Thackeray; 'our southern women are well-favored'- Lillian Hellman <i1201>",
    "id": 1,
    "relations": [{
      "type": "loanword",
      "target": "Filipino: official language of the Philippines; based on Tagalog; draws its lexicon from other Philippine languages <i73061>",
      "relNo": 1
    }],
    "definition": ""
  }],
  "status": "novel",
  "editorId": "jmccrae"
}
