{
  "lemma": "bloop",
  "examples": [{
    "text": "A new favorite : Surface Music On Bloop - Hector Couto ( Guest Mix ) /"
  }, {
    "text": "Bloop"
  }, {
    "text": "BLOOP !"
  }, {
    "text": "with randoms in your snapchat story . # bloop # hellahollywood"
  }, {
    "text": "! # michaelsreality # cocochanel # maltipoos # bloop https : / / t.co / aJDzgeHSvS"
  }, {
    "text": "Bloop RT Neither are u ? RT Lmao Ice"
  }, {
    "text": "# wonderoveryonder beep bloop is getting dangerous close to Fry's dog levels"
  }, {
    "text": "* whirr bloop boop whistle whirr bleep *"
  }, {
    "text": "* beep whistle bloop whistle bloop boop *"
  }, {
    "text": "technically outside international baggage bloop"
  }],
  "status": "",
  "senses": [{
    "pos": "",
    "synonym": "",
    "id": 1,
    "relations": [],
    "definition": ""
  }]
}
