{
  "examples": [{
    "text": "Intergration vs differentiation fuhh ???? killer???"
  }, {
    "text": "to do something about my hair later ... fuhh"
  }, {
    "text": "fuhh"
  }, {
    "text": "Fuhh https : / / t.co / 6G4NyZz1l8"
  }, {
    "text": "Fuhh that would be active asf ????? https :"
  }, {
    "text": "Fuhh penat"
  }, {
    "text": "fuhh drinking soon"
  }],
  "lemma": "fuhh",
  "senses": [{
    "pos": "x",
    "synonym": "",
    "id": 1,
    "relations": [{
      "type": "emotion",
      "target": "exasperation: an exasperated feeling of annoyance <i76267>",
      "relNo": 1
    }],
    "definition": "expression of exasperation"
  }],
  "status": "novel",
  "editorId": "jmccrae"
}
