{
  "lemma": "i want that",
  "examples": [{
    "text": "i want that wig , motherfuck yo hairdo ??"
  }, {
    "text": "I want that pussy for breakfast"
  }, {
    "text": "holy shit I want that"
  }, {
    "text": "like that's a rlly cute tattoo but do I want that on my body for ever ? ¿"
  }, {
    "text": "I want that state championship ring"
  }, {
    "text": "I want that to happen for me"
  }, {
    "text": "I want that mug , swap with mine please https "
  }, {
    "text": "I want that benefit's hoola kit so bad ???"
  }, {
    "text": "I want that old thing back"
  }, {
    "text": "I say , everytime I get near you I want that old thing bac"
  }],
  "status": "","editorId": "",
  "senses": [{
    "pos": "",
    "synonym": "",
    "id": 1,
    "relations": [],
    "definition": ""
  }]
}
