{
  "examples": [{
    "text": "Reporter 2 : Cam , seriously , how sad are yo"
  }, {
    "text": "\\ how sad , you're on house arrest \\\"\" yea yea\""
  }, {
    "text": "How sad is that ?"
  }, {
    "text": "How sad ?"
  }, {
    "text": "how sad https : / / t.co / HMw14hQgLH"
  }, {
    "text": "ESPN is not streaming UM vs FL , how sad "
  }, {
    "text": "Daniel Bryan retired today . I can't express how sad I am . # ThankYouDanielBryan"
  }, {
    "text": "aren't coming to my country do you know how sad that makes me ? : ("
  }, {
    "text": "on my phone are of college work , how sad is my life ma"
  }, {
    "text": "And that's why , no matter how sad the Dreemur family's story might be , I'l"
  }],
  "lemma": "how sad",
  "senses": [{
    "pos": "n",
    "synonym": "",
    "id": 1,
    "relations": [],
    "definition": ""
  }],
  "status": "nonlex",
  "editorId": "jmccrae"
}
