{
  "lemma": "madel",
  "examples": [{
    "text": "# madel # retweets # online # bootypic"
  }, {
    "text": "# madel # upskirt # online # bootypic"
  }, {
    "text": "# bootypic # online # upskirt # madel"
  }, {
    "text": "# madel # upskirt # retweets # bootypic"
  }, {
    "text": "# upskirt # bootypic # madel # online"
  }, {
    "text": "# online # upskirt # madel # bootypic"
  }],
  "status": "","editorId": "",
  "senses": [{
    "pos": "",
    "synonym": "",
    "id": 1,
    "relations": [],
    "definition": ""
  }]
}
