{
  "lemma": "sday",
  "examples": [{
    "text": "Plan for # FoodAllergies at # Valentine ’ sDay Parties https : / / t.co / CVVJBSmonX"
  }, {
    "text": "Book your # Valentine ’ sDay getaway ! 3days 2nights breakfast , pool "
  }, {
    "text": "Nehemiah_IUICVA : # Valentine ’ sDay whom are you worshipping ?"
  }, {
    "text": "# Valentine ’ sDay whom are you worshipping ?"
  }, {
    "text": "to win your love this # Valentine ’ sDay https : / / t.co / xw5v40zWWa"
  }, {
    "text": "Sday i watch bangalore naatkal ."
  }],
  "status": "",
  "senses": [{
    "pos": "",
    "synonym": "",
    "id": 1,
    "relations": [],
    "definition": ""
  }]
}
