{
  "lemma": "matcha",
  "examples": [{
    "text": "https : / / t.co / OMCVargFT0 # matcha # matchola # cleaneating # weightloss # healthy"
  }, {
    "text": "tea activated ! You all know I love matcha green tea ?☺ and I also love …"
  }, {
    "text": "Japan gets new # matcha green tea cream spread"
  }, {
    "text": "LAST DAY to taste our # matcha # eggtart before CNY !"
  }, {
    "text": "Pancake Day - Raspberry Matcha Pancakes https : / / t.co / gUG4lRngz4"
  }, {
    "text": "Organic Matcha Green Tea Powder- Ceremonial Grade Organic USDA Certified"
  }, {
    "text": "Matcha Latte , anyone ? Details https : "
  }, {
    "text": "Janice loves her matcha green tea … https : / / t.co"
  }, {
    "text": "Miracle # Matcha has 3 times the # antioxidant levels of"
  }, {
    "text": "What is your favourite # Matcha drink ? # Discuss # GreenTea : -"
  }],
  "status": "",
  "senses": [{
    "pos": "",
    "synonym": "",
    "id": 1,
    "relations": [],
    "definition": ""
  }]
}
