{
  "lemma": "jerry rice",
  "examples": [{
    "text": "Jerry Rice ! !"
  }, {
    "text": "Jerry Rice looks like he's going back in the Matrix"
  }, {
    "text": "how about jerry rice aqua man goggles #"
  }, {
    "text": "# SB50 Was that Jerry Rice or Cee Lo Green ?"
  }, {
    "text": "Jerry Rice looking like a damn insect with them shades"
  }, {
    "text": "Jerry Rice looks like he's havin a good day !"
  }, {
    "text": "Jerry Rice"
  }, {
    "text": "Jerry Rice"
  }, {
    "text": "I'm going with Jerry Rice , Randy Moss , Megatron , T.O "
  }, {
    "text": "Jerry Rice , Randy Moss , Terrell Owens , Calvi"
  }],
  "status": "","editorId": "",
  "senses": [{
    "pos": "",
    "synonym": "",
    "id": 1,
    "relations": [],
    "definition": ""
  }]
}
