{
  "lemma": "the jungle book",
  "examples": [{
    "text": "THE JUNGLE BOOK Trailer 2 | Disney Movie 2016"
  }, {
    "text": "Check Out ‘ The Jungle Book ’ Super Bowl Trailer https : / /"
  }, {
    "text": "I can't wait to see The Jungle Book that is my favorite movie"
  }, {
    "text": "‘ The Jungle Book ’ Movie 2016 Plot Spoilers : Inside ..."
  }, {
    "text": "The Jungle Book - Trailer 2 - Official Disney | HD"
  }, {
    "text": "The Jungle Book Official Big Game Trailer https : / /"
  }, {
    "text": "The Jungle Book Official Big Game Trailer https : / /"
  }, {
    "text": "Disney ’ s ‘ The Jungle Book ’ Final Poster in ... https : /"
  }, {
    "text": "The Jungle Book International Trailer Mowgli's Adventure : https : /"
  }, {
    "text": "Enchanting , spirited new Disney trailer for ‘ The Jungle Book ’ https : / / t.co / 0CvnpYCUM"
  }],
  "status": "","editorId": "",
  "senses": [{
    "pos": "",
    "synonym": "",
    "id": 1,
    "relations": [],
    "definition": ""
  }]
}
