{
  "lemma": "yardsale",
  "examples": [{
    "text": "# antiques # yardsale Vintage Antique Ladies Home Journal Dress Pattern …"
  }, {
    "text": "# antiques # yardsale Vintage Dovetail Optician's Box With Sliding Cover !"
  }, {
    "text": "# antiques # yardsale Antique Vintage Black Leather Doctor's Bag https :"
  }, {
    "text": "# antique # yardsale 1870s Old Vintage Beautiful Frozen Charlotte Antique Victorian"
  }, {
    "text": "# antique # yardsale ANTIQUE GLASS OIL BURNING LAMP https : /"
  }, {
    "text": "/ / t.co / 8P3z9sY7wM # forsale # yardsale"
  }, {
    "text": "# antiques # yardsale Lot of 4 Vintage Metal Drawer Pulls to"
  }, {
    "text": "# antiques # yardsale Vintage 1960's banjo player planter Antique Made in"
  }, {
    "text": "# antiques # yardsale Vintage Japanese Woodblock Print Hiroshige ' … https"
  }],
  "status": "",
  "senses": [{
    "pos": "",
    "synonym": "",
    "id": 1,
    "relations": [],
    "definition": ""
  }]
}
