{
  "lemma": "bullcrap",
  "examples": [{
    "text": "that's bullcrap"
  }, {
    "text": "lol that's bullcrap but alright"
  }, {
    "text": "BULLCRAP . PEOPLE CAN PUT ANYTHING ON TWITTER.DON'T BELIEVE"
  }, {
    "text": "Blake Shelton tired of the ‘ bullcrap ’ reports about his life https : /"
  }, {
    "text": "that liberal bullcrap preaching is why conservatives stopped subscribing to newspapers"
  }, {
    "text": "Stop with the bullcrap : \\ Hey , it's my twitter .\""
  }, {
    "text": "; all hands on deck ... I call bullcrap Neil Mitchell"
  }],
  "status": "","editorId": "",
  "senses": [{
    "pos": "",
    "synonym": "",
    "id": 1,
    "relations": [],
    "definition": ""
  }]
}
