{
  "lemma": "aren",
  "examples": [{
    "text": "Many Hispanics and Jews aren ’ t White ."
  }, {
    "text": "My Three dogs aren ’ t fancy but god they have a"
  }, {
    "text": "Man Beheads Wife After Discovering Their Six Kids Aren ’ t His https : / / t.co"
  }, {
    "text": "re hitting up against a deadline and things aren ’ t … ” — https : /"
  }, {
    "text": "Taxi Drivers Aren ’ t The Only People Who Should Be"
  }, {
    "text": "“ We aren ’ t addicted to oil , but ou"
  }, {
    "text": "sadgirl2003 : Stop checking on people that aren ’ t checking on you https : /"
  }, {
    "text": "“ How are you really living if you aren ’ t passionate about anything ”"
  }, {
    "text": "Superdelegates : Clinton ’ s major advantage Americans aren ’ t aware of https : / /"
  }, {
    "text": "folks getting marginalized because an algorithm says they aren popular enough ."
  }],
  "status": "",
  "senses": [{
    "pos": "",
    "synonym": "",
    "id": 1,
    "relations": [],
    "definition": ""
  }]
}
