{
  "lemma": "layan",
  "examples": [{
    "text": "haha if it's a friend , layan je la . What are friends for anyway"
  }, {
    "text": "Eu think i very free wan to layan eu all the whike izzit.. i got a"
  }, {
    "text": "best but previous albums are way better . Layan Last Shadow Puppet x ?"
  }, {
    "text": "arguements are really ... something i malas nak layan but.. it's something a lot i have to"
  }, {
    "text": "just understand that i dont have time to layan them sknslejskjwjdncienekdocjf"
  }, {
    "text": "KNN NOISE POLLUTION THE FELLA BESIDE U TKMO LAYAN KAU AH SIA PUKI"
  }],
  "status": "","editorId": "",
  "senses": [{
    "pos": "",
    "synonym": "",
    "id": 1,
    "relations": [],
    "definition": ""
  }]
}
