{
  "lemma": "fuming",
  "examples": [{
    "text": "Charlton fuming after fan forges director ’ s signature of"
  }, {
    "text": "Fuming . Made pancake mix last night and Adams"
  }, {
    "text": "Fuming"
  }, {
    "text": "Fuming"
  }, {
    "text": "I think is FUMING of hunger ... WHERE'S THE FOOD ? !"
  }, {
    "text": "Fuming"
  }, {
    "text": "Fuming"
  }, {
    "text": "Harden gotta be HEATED rn ahahaha that nigga fuming"
  }, {
    "text": "Chicago Breaking Sports ] Joel Quenneville , Blackhawks fuming after overturned goal in 2-0 loss https "
  }, {
    "text": "wonder his Mum & amp ; Aunt are fuming ! # PMQs"
  }],
  "status": "","editorId": "",
  "senses": [{
    "pos": "",
    "synonym": "",
    "id": 1,
    "relations": [],
    "definition": ""
  }]
}
