{
  "lemma": "fucked it",
  "examples": [{
    "text": "2-0 AND YOU FUCKED IT UP ! GGTTH ??? https : / /"
  }, {
    "text": "But he fucked it up ?"
  }, {
    "text": "you fucked it"
  }, {
    "text": "just do another comeback at the one who fucked it up"
  }, {
    "text": "is to watch the line , and he fucked it up . # fixe"
  }, {
    "text": "Fully fucked it ?"
  }, {
    "text": "Fucked it so bad but I'm still doing this early"
  }, {
    "text": "like it's been down since the yajl list fucked it up ."
  }, {
    "text": "almost better and then vaan showed up and fucked it up ."
  }, {
    "text": "i really fucked it up this time , didn't i my dea"
  }],
  "status": "","editorId": "",
  "senses": [{
    "pos": "",
    "synonym": "",
    "id": 1,
    "relations": [],
    "definition": ""
  }]
}
