{
  "lemma": "way too",
  "examples": [{
    "text": "Scream Queens is way too good for my own good"
  }, {
    "text": "way too early"
  }, {
    "text": "I laughed way too hard at this ! ?? https : /"
  }, {
    "text": "Its way too dark in this restaurant"
  }, {
    "text": "i worry about everything way too much"
  }, {
    "text": ". Get home , sudden extreme energy lasting way too long into the night . Sleep at ungodl"
  }, {
    "text": "YAYYYY I CANNOT WAIT ! Been way too long ?"
  }, {
    "text": "Sometimes I worry way too much ."
  }, {
    "text": "wow that ’ s way too much * puts 1 back *"
  }, {
    "text": "wow that ’ s way too much * puts 1 back *"
  }],
  "status": "","editorId": "",
  "senses": [{
    "pos": "",
    "synonym": "",
    "id": 1,
    "relations": [],
    "definition": ""
  }]
}
