{
  "lemma": "ya know",
  "examples": [{
    "text": "Ya know , kinda reminds me of Doloris Avery "
  }, {
    "text": "glomped from behind ... By ... Well , ya know who. "
  }, {
    "text": "just in case I'm getting some , ya know : "
  }, {
    "text": "able to be outspoken and take control . Ya know"
  }, {
    "text": "this will take years ya know lol https : / / t.co / 8u1IaTxNPj"
  }, {
    "text": "how do ya know ?"
  }, {
    "text": "hahahaha ??? pi prefer pandas than pigs ya know ... they're cuter ?"
  }, {
    "text": "So ya know , if you follow me just to ge"
  }, {
    "text": ". disagreeing with any woman is racist.. don't ya know"
  }, {
    "text": "just get another piercing idk but who knows ya know"
  }],
  "status": "","editorId": "",
  "senses": [{
    "pos": "",
    "synonym": "",
    "id": 1,
    "relations": [],
    "definition": ""
  }]
}
