{
  "lemma": "you sleep",
  "examples": [{
    "text": "do more homework but your brain won't let you sleep"
  }, {
    "text": "Lmao , the green arrow real AF bro you slee"
  }, {
    "text": "Me see . Moon get big . You sleep . Sleep out . Out . All you"
  }, {
    "text": "On your skin , skin while you sleep , u"
  }, {
    "text": "Catch you while you sleep , turn your sheets to maroon sheets .."
  }, {
    "text": "you sleep well too and I love you so much"
  }, {
    "text": "A S / / I LIKE IT WHEN YOU SLEEP FOR YOU ARE SO BEAUTIFUL AND YET SO"
  }, {
    "text": "No one should fucking care if you sleep with 10 people a day or with no"
  }],
  "status": "","editorId": "",
  "senses": [{
    "pos": "",
    "synonym": "",
    "id": 1,
    "relations": [],
    "definition": ""
  }]
}
